lyrica_labs_nexa_llm-0.2.0.dist-info/licenses/LICENSE
lyricalabs/__init__.py
lyricalabs/client.py
lyrica_labs_nexa_llm-0.2.0.dist-info/METADATA
lyrica_labs_nexa_llm-0.2.0.dist-info/WHEEL
lyrica_labs_nexa_llm-0.2.0.dist-info/top_level.txt
lyrica_labs_nexa_llm-0.2.0.dist-info/RECORD
