Metadata-Version: 2.4
Name: Lyrica_Labs_Nexa_LLM
Version: 0.2.0
Summary: Nexa: Lyrica Labs tarafından eğitilmiş geniş veri LLM Python kütüphanesi
Home-page: https://lyricalabs.vercel.app/nexa
Author: Lyrica Labs
Author-email: lyricalabs@gmail.com
License: MIT
Requires-Python: >=3.8
License-File: LICENSE
Requires-Dist: requests
Dynamic: author
Dynamic: author-email
Dynamic: home-page
Dynamic: license
Dynamic: license-file
Dynamic: requires-dist
Dynamic: requires-python
Dynamic: summary
